[
  {
    "id": 1,
    "zone": "Europe/London",
    "country": "UK",
    "city": "London"
  },
  {
    "id": 2,
    "zone": "Europe/Berlin",
    "country": "Germany",
    "city": "Berlin"
  },
  {
    "id": 3,
    "zone": "Europe/Moscow",
    "country": "Russia",
    "city": "Moscow"
  },
  {
    "id": 4,
    "zone": "Asia/Qatar",
    "country": "Qatar",
    "city": "Doha"
  },
  {
    "id": 5,
    "zone": "Asia/Hong_Kong",
    "country": "China",
    "city": "Hong Kong"
  },
  {
    "id": 6,
    "zone": "Australia/Sydney",
    "country": "Australia",
    "city": "Sydney"
  },
  {
    "id": 7,
    "zone": "America/Los_Angeles",
    "country": "USA",
    "city": "Los Angeles"
  },
  {
    "id": 8,
    "zone": "America/New_York",
    "country": "USA",
    "city": "New York"
  }
]